django_only_staff-0.1.0.dist-info/DESCRIPTION.rst
django_only_staff-0.1.0.dist-info/METADATA
django_only_staff-0.1.0.dist-info/RECORD
django_only_staff-0.1.0.dist-info/WHEEL
django_only_staff-0.1.0.dist-info/metadata.json
django_only_staff-0.1.0.dist-info/top_level.txt
only_staff/__init__.py
only_staff/middleware.py
